{
    "pipes": [],
    "interfaces": [
        {
            "name": "Task",
            "id": "interface-Task-1ad0cecba04479736c8496e599ff134330e37e5718ce31567199139835086dc3eb48fae9f845e4b696c7a1972ff55cc786746dd409526f26725e9af37c180bb1",
            "file": "src/app/models/task.model.ts",
            "deprecated": false,
            "deprecationMessage": "",
            "type": "interface",
            "sourceCode": "export interface Task {\n    id: number,\n    title: string,\n    completed: boolean,\n    editing?: boolean\n}",
            "properties": [
                {
                    "name": "completed",
                    "deprecated": false,
                    "deprecationMessage": "",
                    "type": "boolean",
                    "optional": false,
                    "description": "",
                    "line": 4
                },
                {
                    "name": "editing",
                    "deprecated": false,
                    "deprecationMessage": "",
                    "type": "boolean",
                    "optional": true,
                    "description": "",
                    "line": 5
                },
                {
                    "name": "id",
                    "deprecated": false,
                    "deprecationMessage": "",
                    "type": "number",
                    "optional": false,
                    "description": "",
                    "line": 2
                },
                {
                    "name": "title",
                    "deprecated": false,
                    "deprecationMessage": "",
                    "type": "string",
                    "optional": false,
                    "description": "",
                    "line": 3
                }
            ],
            "indexSignatures": [],
            "kind": 171,
            "methods": [],
            "extends": []
        },
        {
            "name": "User",
            "id": "interface-User-d4821beac0e4a852e513391b7470981c4353fdd95a18628bb68136c8695b489ee15b926e2e5031bc26cf30e1508e0a362c3ee13a06734702b4d15af140e485d5",
            "file": "src/stories/user.ts",
            "deprecated": false,
            "deprecationMessage": "",
            "type": "interface",
            "sourceCode": "export interface User {\n  name: string;\n}\n",
            "properties": [
                {
                    "name": "name",
                    "deprecated": false,
                    "deprecationMessage": "",
                    "type": "string",
                    "optional": false,
                    "description": "",
                    "line": 2
                }
            ],
            "indexSignatures": [],
            "kind": 171,
            "methods": [],
            "extends": []
        }
    ],
    "injectables": [],
    "guards": [],
    "interceptors": [],
    "classes": [],
    "directives": [],
    "components": [
        {
            "name": "AppComponent",
            "id": "component-AppComponent-b4c06a22d7d26024d211b74593555268f278b4b5fcfbf39a5fdfe9d907834b57330f4536734c5e086c1d069f63c14e675633b40f42fad3b8a5e1a927c6fee7a1",
            "file": "src/app/app.component.ts",
            "encapsulation": [],
            "entryComponents": [],
            "inputs": [],
            "outputs": [],
            "providers": [],
            "selector": "app-root",
            "styleUrls": [],
            "styles": [],
            "templateUrl": [
                "./app.component.html"
            ],
            "viewProviders": [],
            "hostDirectives": [],
            "inputsClass": [],
            "outputsClass": [],
            "propertiesClass": [],
            "methodsClass": [],
            "deprecated": false,
            "deprecationMessage": "",
            "hostBindings": [],
            "hostListeners": [],
            "standalone": true,
            "imports": [
                {
                    "name": "CommonModule",
                    "type": "module"
                },
                {
                    "name": "RouterOutlet"
                }
            ],
            "description": "",
            "rawdescription": "\n",
            "type": "component",
            "sourceCode": "import { Component } from '@angular/core';\nimport { CommonModule } from '@angular/common';\nimport { RouterOutlet } from '@angular/router';\n\n@Component({\n  selector: 'app-root',\n  standalone: true,\n  imports: [CommonModule, RouterOutlet],\n  templateUrl: './app.component.html',\n  styleUrl: './app.component.scss'\n})\nexport class AppComponent {\n  \n}\n",
            "styleUrl": "./app.component.scss",
            "assetsDirs": [],
            "styleUrlsData": "",
            "stylesData": "",
            "extends": [],
            "templateData": "<router-outlet></router-outlet>"
        },
        {
            "name": "ButtonComponent",
            "id": "component-ButtonComponent-86e2311c54fbca7431c12e070d0fd5b0ebe343eec0553a392f182ba0e04a8f86613233d26ee47718fd0e7a65078f580c76a1fcc928ce55de81193d6618025bc4",
            "file": "src/stories/button.component.ts",
            "encapsulation": [],
            "entryComponents": [],
            "inputs": [],
            "outputs": [],
            "providers": [],
            "selector": "storybook-button",
            "styleUrls": [
                "./button.css"
            ],
            "styles": [],
            "template": "<button   type=\"button\"\n   (click)=\"onClick.emit($event)\"\n   [ngClass]=\"classes\"\n   [ngStyle]=\"{ 'background-color': backgroundColor }\"\n >\n   {{ label }}\n </button>",
            "templateUrl": [],
            "viewProviders": [],
            "hostDirectives": [],
            "inputsClass": [
                {
                    "name": "backgroundColor",
                    "deprecated": false,
                    "deprecationMessage": "",
                    "rawdescription": "\n\nWhat background color to use\n",
                    "description": "<p>What background color to use</p>\n",
                    "line": 29,
                    "type": "string",
                    "decorators": []
                },
                {
                    "name": "label",
                    "defaultValue": "'Button'",
                    "deprecated": false,
                    "deprecationMessage": "",
                    "jsdoctags": [
                        {
                            "pos": 798,
                            "end": 811,
                            "flags": 16842752,
                            "modifierFlagsCache": 0,
                            "transformFlags": 0,
                            "kind": 334,
                            "tagName": {
                                "pos": 799,
                                "end": 807,
                                "flags": 16842752,
                                "modifierFlagsCache": 0,
                                "transformFlags": 0,
                                "kind": 80,
                                "escapedText": "required"
                            },
                            "comment": ""
                        }
                    ],
                    "rawdescription": "\n\nButton contents\n\n",
                    "description": "<p>Button contents</p>\n",
                    "line": 43,
                    "type": "string",
                    "decorators": []
                },
                {
                    "name": "primary",
                    "defaultValue": "false",
                    "deprecated": false,
                    "deprecationMessage": "",
                    "rawdescription": "\n\nIs this the principal call to action on the page?\n",
                    "description": "<p>Is this the principal call to action on the page?</p>\n",
                    "line": 23,
                    "type": "boolean",
                    "decorators": []
                },
                {
                    "name": "size",
                    "defaultValue": "'medium'",
                    "deprecated": false,
                    "deprecationMessage": "",
                    "rawdescription": "\n\nHow large should the button be?\n",
                    "description": "<p>How large should the button be?</p>\n",
                    "line": 35,
                    "type": "\"small\" | \"medium\" | \"large\"",
                    "decorators": []
                }
            ],
            "outputsClass": [
                {
                    "name": "onClick",
                    "defaultValue": "new EventEmitter<Event>()",
                    "deprecated": false,
                    "deprecationMessage": "",
                    "rawdescription": "\n\nOptional click handler\n",
                    "description": "<p>Optional click handler</p>\n",
                    "line": 49,
                    "type": "EventEmitter"
                }
            ],
            "propertiesClass": [],
            "methodsClass": [],
            "deprecated": false,
            "deprecationMessage": "",
            "hostBindings": [],
            "hostListeners": [],
            "standalone": true,
            "imports": [
                {
                    "name": "CommonModule",
                    "type": "module"
                }
            ],
            "description": "",
            "rawdescription": "\n",
            "type": "component",
            "sourceCode": "import { CommonModule } from '@angular/common';\nimport { Component, Input, Output, EventEmitter } from '@angular/core';\n\n@Component({\n  selector: 'storybook-button',\n  standalone: true,\n  imports: [CommonModule],\n  template: ` <button\n    type=\"button\"\n    (click)=\"onClick.emit($event)\"\n    [ngClass]=\"classes\"\n    [ngStyle]=\"{ 'background-color': backgroundColor }\"\n  >\n    {{ label }}\n  </button>`,\n  styleUrls: ['./button.css'],\n})\nexport class ButtonComponent {\n  /**\n   * Is this the principal call to action on the page?\n   */\n  @Input()\n  primary = false;\n\n  /**\n   * What background color to use\n   */\n  @Input()\n  backgroundColor?: string;\n\n  /**\n   * How large should the button be?\n   */\n  @Input()\n  size: 'small' | 'medium' | 'large' = 'medium';\n\n  /**\n   * Button contents\n   *\n   * @required\n   */\n  @Input()\n  label = 'Button';\n\n  /**\n   * Optional click handler\n   */\n  @Output()\n  onClick = new EventEmitter<Event>();\n\n  public get classes(): string[] {\n    const mode = this.primary ? 'storybook-button--primary' : 'storybook-button--secondary';\n\n    return ['storybook-button', `storybook-button--${this.size}`, mode];\n  }\n}\n",
            "assetsDirs": [],
            "styleUrlsData": [
                {
                    "data": ".storybook-button {\n  font-family: 'Nunito Sans', 'Helvetica Neue', Helvetica, Arial, sans-serif;\n  font-weight: 700;\n  border: 0;\n  border-radius: 3em;\n  cursor: pointer;\n  display: inline-block;\n  line-height: 1;\n}\n.storybook-button--primary {\n  color: white;\n  background-color: #1ea7fd;\n}\n.storybook-button--secondary {\n  color: #333;\n  background-color: transparent;\n  box-shadow: rgba(0, 0, 0, 0.15) 0px 0px 0px 1px inset;\n}\n.storybook-button--small {\n  font-size: 12px;\n  padding: 10px 16px;\n}\n.storybook-button--medium {\n  font-size: 14px;\n  padding: 11px 20px;\n}\n.storybook-button--large {\n  font-size: 16px;\n  padding: 12px 24px;\n}\n",
                    "styleUrl": "./button.css"
                }
            ],
            "stylesData": "",
            "extends": [],
            "accessors": {
                "classes": {
                    "name": "classes",
                    "getSignature": {
                        "name": "classes",
                        "type": "[]",
                        "returnType": "string[]",
                        "line": 51
                    }
                }
            }
        },
        {
            "name": "HeaderComponent",
            "id": "component-HeaderComponent-cad94b233ec8e80ceb541e7972c5f9737e08237b4e137112f3987ca48ee0cce5c0d57798d41daa5d4d24d6bdbb2df1606ab68cca2aa0a1785e38f99f3cac0729",
            "file": "src/stories/header.component.ts",
            "encapsulation": [],
            "entryComponents": [],
            "inputs": [],
            "outputs": [],
            "providers": [],
            "selector": "storybook-header",
            "styleUrls": [
                "./header.css"
            ],
            "styles": [],
            "template": "<header>    <div class=\"storybook-header\">\n      <div>\n        <svg width=\"32\" height=\"32\" viewBox=\"0 0 32 32\" xmlns=\"http://www.w3.org/2000/svg\">\n          <g fill=\"none\" fillRule=\"evenodd\">\n            <path\n              d=\"M10 0h12a10 10 0 0110 10v12a10 10 0 01-10 10H10A10 10 0 010 22V10A10 10 0 0110 0z\"\n              fill=\"#FFF\"\n            />\n            <path\n              d=\"M5.3 10.6l10.4 6v11.1l-10.4-6v-11zm11.4-6.2l9.7 5.5-9.7 5.6V4.4z\"\n              fill=\"#555AB9\"\n            />\n            <path\n              d=\"M27.2 10.6v11.2l-10.5 6V16.5l10.5-6zM15.7 4.4v11L6 10l9.7-5.5z\"\n              fill=\"#91BAF8\"\n            />\n          </g>\n        </svg>\n        <h1>Acme</h1>\n      </div>\n      <div>\n        <div *ngIf=\"user\">\n          <span class=\"welcome\">\n            Welcome, <b>{{ user.name }}</b\n            >!\n          </span>\n          <storybook-button\n            *ngIf=\"user\"\n            size=\"small\"\n            (onClick)=\"onLogout.emit($event)\"\n            label=\"Log out\"\n          ></storybook-button>\n        </div>\n        <div *ngIf=\"!user\">\n          <storybook-button\n            *ngIf=\"!user\"\n            size=\"small\"\n            class=\"margin-left\"\n            (onClick)=\"onLogin.emit($event)\"\n            label=\"Log in\"\n          ></storybook-button>\n          <storybook-button\n            *ngIf=\"!user\"\n            size=\"small\"\n            [primary]=\"true\"\n            class=\"margin-left\"\n            (onClick)=\"onCreateAccount.emit($event)\"\n            label=\"Sign up\"\n          ></storybook-button>\n        </div>\n      </div>\n    </div>\n  </header>",
            "templateUrl": [],
            "viewProviders": [],
            "hostDirectives": [],
            "inputsClass": [
                {
                    "name": "user",
                    "defaultValue": "null",
                    "deprecated": false,
                    "deprecationMessage": "",
                    "line": 69,
                    "type": "User | null",
                    "decorators": []
                }
            ],
            "outputsClass": [
                {
                    "name": "onCreateAccount",
                    "defaultValue": "new EventEmitter<Event>()",
                    "deprecated": false,
                    "deprecationMessage": "",
                    "line": 78,
                    "type": "EventEmitter"
                },
                {
                    "name": "onLogin",
                    "defaultValue": "new EventEmitter<Event>()",
                    "deprecated": false,
                    "deprecationMessage": "",
                    "line": 72,
                    "type": "EventEmitter"
                },
                {
                    "name": "onLogout",
                    "defaultValue": "new EventEmitter<Event>()",
                    "deprecated": false,
                    "deprecationMessage": "",
                    "line": 75,
                    "type": "EventEmitter"
                }
            ],
            "propertiesClass": [],
            "methodsClass": [],
            "deprecated": false,
            "deprecationMessage": "",
            "hostBindings": [],
            "hostListeners": [],
            "standalone": true,
            "imports": [
                {
                    "name": "CommonModule",
                    "type": "module"
                },
                {
                    "name": "ButtonComponent",
                    "type": "component"
                }
            ],
            "description": "",
            "rawdescription": "\n",
            "type": "component",
            "sourceCode": "import { Component, Input, Output, EventEmitter } from '@angular/core';\nimport { CommonModule } from '@angular/common';\n\nimport { ButtonComponent } from './button.component';\nimport type { User } from './user';\n\n@Component({\n  selector: 'storybook-header',\n  standalone: true,\n  imports: [CommonModule, ButtonComponent],\n  template: `<header>\n    <div class=\"storybook-header\">\n      <div>\n        <svg width=\"32\" height=\"32\" viewBox=\"0 0 32 32\" xmlns=\"http://www.w3.org/2000/svg\">\n          <g fill=\"none\" fillRule=\"evenodd\">\n            <path\n              d=\"M10 0h12a10 10 0 0110 10v12a10 10 0 01-10 10H10A10 10 0 010 22V10A10 10 0 0110 0z\"\n              fill=\"#FFF\"\n            />\n            <path\n              d=\"M5.3 10.6l10.4 6v11.1l-10.4-6v-11zm11.4-6.2l9.7 5.5-9.7 5.6V4.4z\"\n              fill=\"#555AB9\"\n            />\n            <path\n              d=\"M27.2 10.6v11.2l-10.5 6V16.5l10.5-6zM15.7 4.4v11L6 10l9.7-5.5z\"\n              fill=\"#91BAF8\"\n            />\n          </g>\n        </svg>\n        <h1>Acme</h1>\n      </div>\n      <div>\n        <div *ngIf=\"user\">\n          <span class=\"welcome\">\n            Welcome, <b>{{ user.name }}</b\n            >!\n          </span>\n          <storybook-button\n            *ngIf=\"user\"\n            size=\"small\"\n            (onClick)=\"onLogout.emit($event)\"\n            label=\"Log out\"\n          ></storybook-button>\n        </div>\n        <div *ngIf=\"!user\">\n          <storybook-button\n            *ngIf=\"!user\"\n            size=\"small\"\n            class=\"margin-left\"\n            (onClick)=\"onLogin.emit($event)\"\n            label=\"Log in\"\n          ></storybook-button>\n          <storybook-button\n            *ngIf=\"!user\"\n            size=\"small\"\n            [primary]=\"true\"\n            class=\"margin-left\"\n            (onClick)=\"onCreateAccount.emit($event)\"\n            label=\"Sign up\"\n          ></storybook-button>\n        </div>\n      </div>\n    </div>\n  </header>`,\n  styleUrls: ['./header.css'],\n})\nexport class HeaderComponent {\n  @Input()\n  user: User | null = null;\n\n  @Output()\n  onLogin = new EventEmitter<Event>();\n\n  @Output()\n  onLogout = new EventEmitter<Event>();\n\n  @Output()\n  onCreateAccount = new EventEmitter<Event>();\n}\n",
            "assetsDirs": [],
            "styleUrlsData": [
                {
                    "data": ".storybook-header {\n  font-family: 'Nunito Sans', 'Helvetica Neue', Helvetica, Arial, sans-serif;\n  border-bottom: 1px solid rgba(0, 0, 0, 0.1);\n  padding: 15px 20px;\n  display: flex;\n  align-items: center;\n  justify-content: space-between;\n}\n\n.storybook-header svg {\n  display: inline-block;\n  vertical-align: top;\n}\n\n.storybook-header h1 {\n  font-weight: 700;\n  font-size: 20px;\n  line-height: 1;\n  margin: 6px 0 6px 10px;\n  display: inline-block;\n  vertical-align: top;\n}\n\n.storybook-header button + button {\n  margin-left: 10px;\n}\n\n.storybook-header .welcome {\n  color: #333;\n  font-size: 14px;\n  margin-right: 10px;\n}\n",
                    "styleUrl": "./header.css"
                }
            ],
            "stylesData": "",
            "extends": []
        },
        {
            "name": "HomeComponent",
            "id": "component-HomeComponent-93eb3069a4f62bb21e92b6b80bee60b11fba255c4b7265b5a8c55c4fe81e01a6aed296dda8c7eaf436d190dd7f6a407d664150d6f03dcd73e7c0d75289fde7ae",
            "file": "src/app/pages/home/home.component.ts",
            "encapsulation": [],
            "entryComponents": [],
            "inputs": [],
            "outputs": [],
            "providers": [],
            "selector": "app-home",
            "styleUrls": [],
            "styles": [],
            "templateUrl": [
                "./home.component.html"
            ],
            "viewProviders": [],
            "hostDirectives": [],
            "inputsClass": [],
            "outputsClass": [],
            "propertiesClass": [
                {
                    "name": "filter",
                    "defaultValue": "signal(FilterEnum.ALL)",
                    "deprecated": false,
                    "deprecationMessage": "",
                    "type": "",
                    "optional": false,
                    "description": "",
                    "line": 17
                },
                {
                    "name": "filterEnum",
                    "defaultValue": "FilterEnum",
                    "deprecated": false,
                    "deprecationMessage": "",
                    "type": "",
                    "optional": false,
                    "description": "",
                    "line": 16
                },
                {
                    "name": "injector",
                    "defaultValue": "inject(Injector)",
                    "deprecated": false,
                    "deprecationMessage": "",
                    "type": "",
                    "optional": false,
                    "description": "",
                    "line": 37
                },
                {
                    "name": "newTaskControl",
                    "defaultValue": "new FormControl('', {\n    nonNullable: true,\n    validators: [\n      Validators.required\n    ]\n  })",
                    "deprecated": false,
                    "deprecationMessage": "",
                    "type": "",
                    "optional": false,
                    "description": "",
                    "line": 30
                },
                {
                    "name": "taskByFilter",
                    "defaultValue": "computed( () => {\n    const currentFilter = this.filter();\n    const tasks = this.tasks();\n    if (currentFilter === FilterEnum.PENDING) {\n      return this.tasks().filter(task => !task.completed);\n    } else if (currentFilter === FilterEnum.COMPLETED) {\n      return this.tasks().filter(task => task.completed);\n    } else {\n      return tasks;\n    }\n  })",
                    "deprecated": false,
                    "deprecationMessage": "",
                    "type": "",
                    "optional": false,
                    "description": "",
                    "line": 19
                },
                {
                    "name": "tasks",
                    "defaultValue": "signal<Task[]>([])",
                    "deprecated": false,
                    "deprecationMessage": "",
                    "type": "",
                    "optional": false,
                    "description": "",
                    "line": 18
                }
            ],
            "methodsClass": [
                {
                    "name": "addTask",
                    "args": [
                        {
                            "name": "title",
                            "type": "string",
                            "deprecated": false,
                            "deprecationMessage": ""
                        }
                    ],
                    "optional": false,
                    "returnType": "void",
                    "typeParameters": [],
                    "line": 71,
                    "deprecated": false,
                    "deprecationMessage": "",
                    "jsdoctags": [
                        {
                            "name": "title",
                            "type": "string",
                            "deprecated": false,
                            "deprecationMessage": "",
                            "tagName": {
                                "text": "param"
                            }
                        }
                    ]
                },
                {
                    "name": "changeFilter",
                    "args": [
                        {
                            "name": "filter",
                            "type": "FilterEnum",
                            "deprecated": false,
                            "deprecationMessage": ""
                        }
                    ],
                    "optional": false,
                    "returnType": "void",
                    "typeParameters": [],
                    "line": 128,
                    "deprecated": false,
                    "deprecationMessage": "",
                    "jsdoctags": [
                        {
                            "name": "filter",
                            "type": "FilterEnum",
                            "deprecated": false,
                            "deprecationMessage": "",
                            "tagName": {
                                "text": "param"
                            }
                        }
                    ]
                },
                {
                    "name": "changeHandler",
                    "args": [
                        {
                            "name": "event",
                            "type": "Event",
                            "deprecated": false,
                            "deprecationMessage": ""
                        }
                    ],
                    "optional": false,
                    "returnType": "void",
                    "typeParameters": [],
                    "line": 56,
                    "deprecated": false,
                    "deprecationMessage": "",
                    "jsdoctags": [
                        {
                            "name": "event",
                            "type": "Event",
                            "deprecated": false,
                            "deprecationMessage": "",
                            "tagName": {
                                "text": "param"
                            }
                        }
                    ]
                },
                {
                    "name": "clearCompleted",
                    "args": [],
                    "optional": false,
                    "returnType": "void",
                    "typeParameters": [],
                    "line": 132,
                    "deprecated": false,
                    "deprecationMessage": ""
                },
                {
                    "name": "deleteTask",
                    "args": [
                        {
                            "name": "index",
                            "type": "number",
                            "deprecated": false,
                            "deprecationMessage": ""
                        }
                    ],
                    "optional": false,
                    "returnType": "void",
                    "typeParameters": [],
                    "line": 80,
                    "deprecated": false,
                    "deprecationMessage": "",
                    "jsdoctags": [
                        {
                            "name": "index",
                            "type": "number",
                            "deprecated": false,
                            "deprecationMessage": "",
                            "tagName": {
                                "text": "param"
                            }
                        }
                    ]
                },
                {
                    "name": "ngOnInit",
                    "args": [],
                    "optional": false,
                    "returnType": "void",
                    "typeParameters": [],
                    "line": 39,
                    "deprecated": false,
                    "deprecationMessage": ""
                },
                {
                    "name": "trackTasks",
                    "args": [],
                    "optional": false,
                    "returnType": "void",
                    "typeParameters": [],
                    "line": 48,
                    "deprecated": false,
                    "deprecationMessage": ""
                },
                {
                    "name": "updateTask",
                    "args": [
                        {
                            "name": "index",
                            "type": "number",
                            "deprecated": false,
                            "deprecationMessage": ""
                        }
                    ],
                    "optional": false,
                    "returnType": "void",
                    "typeParameters": [],
                    "line": 87,
                    "deprecated": false,
                    "deprecationMessage": "",
                    "jsdoctags": [
                        {
                            "name": "index",
                            "type": "number",
                            "deprecated": false,
                            "deprecationMessage": "",
                            "tagName": {
                                "text": "param"
                            }
                        }
                    ]
                },
                {
                    "name": "updateTaskEditingMode",
                    "args": [
                        {
                            "name": "index",
                            "type": "number",
                            "deprecated": false,
                            "deprecationMessage": ""
                        }
                    ],
                    "optional": false,
                    "returnType": "void",
                    "typeParameters": [],
                    "line": 100,
                    "deprecated": false,
                    "deprecationMessage": "",
                    "jsdoctags": [
                        {
                            "name": "index",
                            "type": "number",
                            "deprecated": false,
                            "deprecationMessage": "",
                            "tagName": {
                                "text": "param"
                            }
                        }
                    ]
                },
                {
                    "name": "updateTaskText",
                    "args": [
                        {
                            "name": "index",
                            "type": "number",
                            "deprecated": false,
                            "deprecationMessage": ""
                        },
                        {
                            "name": "event",
                            "type": "Event",
                            "deprecated": false,
                            "deprecationMessage": ""
                        }
                    ],
                    "optional": false,
                    "returnType": "void",
                    "typeParameters": [],
                    "line": 111,
                    "deprecated": false,
                    "deprecationMessage": "",
                    "jsdoctags": [
                        {
                            "name": "index",
                            "type": "number",
                            "deprecated": false,
                            "deprecationMessage": "",
                            "tagName": {
                                "text": "param"
                            }
                        },
                        {
                            "name": "event",
                            "type": "Event",
                            "deprecated": false,
                            "deprecationMessage": "",
                            "tagName": {
                                "text": "param"
                            }
                        }
                    ]
                },
                {
                    "name": "updateTaskText2",
                    "args": [
                        {
                            "name": "index",
                            "type": "number",
                            "deprecated": false,
                            "deprecationMessage": ""
                        },
                        {
                            "name": "event",
                            "type": "Event",
                            "deprecated": false,
                            "deprecationMessage": ""
                        },
                        {
                            "name": "task",
                            "type": "Task",
                            "deprecated": false,
                            "deprecationMessage": ""
                        }
                    ],
                    "optional": false,
                    "returnType": "void",
                    "typeParameters": [],
                    "line": 122,
                    "deprecated": false,
                    "deprecationMessage": "",
                    "jsdoctags": [
                        {
                            "name": "index",
                            "type": "number",
                            "deprecated": false,
                            "deprecationMessage": "",
                            "tagName": {
                                "text": "param"
                            }
                        },
                        {
                            "name": "event",
                            "type": "Event",
                            "deprecated": false,
                            "deprecationMessage": "",
                            "tagName": {
                                "text": "param"
                            }
                        },
                        {
                            "name": "task",
                            "type": "Task",
                            "deprecated": false,
                            "deprecationMessage": "",
                            "tagName": {
                                "text": "param"
                            }
                        }
                    ]
                }
            ],
            "deprecated": false,
            "deprecationMessage": "",
            "hostBindings": [],
            "hostListeners": [],
            "standalone": true,
            "imports": [
                {
                    "name": "CommonModule",
                    "type": "module"
                },
                {
                    "name": "ReactiveFormsModule",
                    "type": "module"
                }
            ],
            "description": "",
            "rawdescription": "\n",
            "type": "component",
            "sourceCode": "import { CommonModule } from '@angular/common';\nimport { Component, Injector, computed, effect, inject, signal } from '@angular/core';\nimport { Task } from '../../models/task.model';\nimport { FormControl, ReactiveFormsModule, Validators } from '@angular/forms';\nimport { FilterEnum } from '../../enums/filtes.enum';\n\n@Component({\n  selector: 'app-home',\n  standalone: true,\n  imports: [CommonModule, ReactiveFormsModule],\n  templateUrl: './home.component.html',\n  styleUrl: './home.component.scss'\n})\nexport class HomeComponent {\n\n  filterEnum = FilterEnum;\n  filter = signal(FilterEnum.ALL);\n  tasks = signal<Task[]>([]);\n  taskByFilter = computed( () => {\n    const currentFilter = this.filter();\n    const tasks = this.tasks();\n    if (currentFilter === FilterEnum.PENDING) {\n      return this.tasks().filter(task => !task.completed);\n    } else if (currentFilter === FilterEnum.COMPLETED) {\n      return this.tasks().filter(task => task.completed);\n    } else {\n      return tasks;\n    }\n  });\n  newTaskControl = new FormControl('', {\n    nonNullable: true,\n    validators: [\n      Validators.required\n    ]\n  });\n\n  injector = inject(Injector);\n\n  ngOnInit() {\n    const storage = localStorage.getItem('tasks');\n    if (storage) {\n      const tasks: Task[] = JSON.parse(storage);\n      this.tasks.set(tasks);\n    }\n    this.trackTasks()\n  }\n\n  trackTasks() {\n    effect( () => {\n      const tasks = this.tasks();\n      console.log(tasks);\n      localStorage.setItem('tasks', JSON.stringify(tasks));\n    }, {injector: this.injector})\n  }\n\n  changeHandler(event: Event) {\n    if (this.newTaskControl.valid) {\n      const value = this.newTaskControl.value.trim();\n      if (value.length > 0) {\n        this.addTask(value);\n        this.newTaskControl.setValue('');\n      }\n    }\n    // const input = event.target as HTMLInputElement;\n    // const newTask = input.value;\n    // if (newTask.trim().length > 0) {\n    //   this.addTask(newTask);\n    // }\n  }\n\n  addTask(title: string) {\n    const newTask = {\n      id: Date.now(),\n      title: title,\n      completed: false\n    }\n    this.tasks.update(prevState => [...prevState, newTask]);\n  }\n\n  deleteTask(index: number) {\n    this.tasks.update((tasks) => tasks.filter((task, position) => position !== index));\n    // this.tasks.mutate(state => {\n    //   state.splice(index, 1);\n    // })\n  }\n\n  updateTask(index: number) {\n    this.tasks.update(tasks => {\n      return tasks.map( (task, position) => {\n        if (position === index) {\n          return {\n            ...task, completed: !task.completed\n          }\n        }\n        return task;\n      })\n    });\n  }\n\n  updateTaskEditingMode(index: number) {\n    this.tasks.update(tasks => {\n      return tasks.map( (task, position) => {\n        if (position === index && !task.completed) {\n          return {...task, editing: true}\n        }\n        return {...task, editing: false}\n      })\n    })\n  }\n\n  updateTaskText(index: number, event: Event) {\n    const input = event.target as HTMLInputElement;\n    this.tasks.update(prevState => {\n      return prevState.map( (task, position) => {\n        if (position === index) {\n          return { ...task, title: input.value, editing: false}\n        }\n        return task;\n      });\n    })\n  }\n  updateTaskText2(index: number,event: Event, task: Task) {\n      const input = event.target as HTMLInputElement;\n      task.title = input.value;\n      task.editing = false;\n  }\n\n  changeFilter(filter: FilterEnum) {\n    this.filter.set(filter);\n  }\n\n  clearCompleted() {\n    this.tasks.update( tasks => tasks.filter(task => !task.completed));\n  }\n\n}\n",
            "styleUrl": "./home.component.scss",
            "assetsDirs": [],
            "styleUrlsData": "",
            "stylesData": "",
            "extends": [],
            "templateData": "<section class=\"todoapp\">\n    <header class=\"header\">\n      <div class=\"container\">\n        <h1>My Day</h1>\n        <p>All my tasks in one place</p>\n        <input\n          class=\"new-todo\"\n          placeholder=\"Type new todo\"\n          autofocus\n          type=\"text\"\n          [formControl]=\"newTaskControl\"\n          (change)=\"changeHandler($event)\"\n        />\n      </div>\n    </header>\n    <div class=\"container todoapp-wrapper\">\n      <!-- This section should be hidden by default and shown when there are todos -->\n      <!-- <pre>\n        <code>\n          {{ tasks() | json }}\n        </code>\n      </pre> -->\n      <section class=\"main\">\n        <ul class=\"todo-list\">\n          <li  (dblclick)=\"updateTaskEditingMode(i)\"\n                *ngFor=\"let task of taskByFilter(); index as i\" \n                [class.editing]=\"task.editing\"\n                [class.completed]=\"task.completed\">\n            <div class=\"view\">\n              <input class=\"toggle\" type=\"checkbox\" [checked]=\"task.completed\" (change)=\"updateTask(i)\" />\n              <label>{{ task.title }}</label>\n              <button class=\"destroy\" (click)=\"deleteTask(i)\"></button>\n            </div>\n            <input class=\"edit\" [value]=\"task.title\" (keydown.enter)=\"updateTaskText(i, $event)\"/>\n          </li>\n        \n        </ul>\n      </section>\n      \n      <footer class=\"footer\">\n        <!-- This should be `0 items left` by default -->\n        <span class=\"todo-count\">\n            <strong> {{taskByFilter().length}}</strong> {{ taskByFilter().length === 1 ? 'item' : 'items' }}\n        </span>\n        <!-- Remove this if you don't implement routing -->\n        <ul class=\"filters\">\n          <li>\n            <a (click)=\"changeFilter(filterEnum.ALL)\" [class.selected]=\"filter() === filterEnum.ALL\">All</a>\n          </li>\n          <li>\n            <a (click)=\"changeFilter(filterEnum.PENDING)\" [class.selected]=\"filter() === filterEnum.PENDING\">Pending</a>\n          </li>\n          <li>\n            <a (click)=\"changeFilter(filterEnum.COMPLETED)\" [class.selected]=\"filter() === filterEnum.COMPLETED\">Completed</a>\n          </li>\n        </ul>\n        <!-- Hidden if no completed items are left ↓ -->\n        <button class=\"clear-completed\" (click)=\"clearCompleted()\">Clear completed</button>\n      </footer>\n    </div>\n  </section>"
        },
        {
            "name": "LabsComponent",
            "id": "component-LabsComponent-b0a9b8cb025b8da3d4d822e2ec874665c6796997d377dd556f6ea7db9f108fa74e4c40b9d4934731a52d3f17493c018a0963cc7af1690240f3497e7d9b9af96d",
            "file": "src/app/pages/labs/labs.component.ts",
            "encapsulation": [],
            "entryComponents": [],
            "inputs": [],
            "outputs": [],
            "providers": [],
            "selector": "app-labs",
            "styleUrls": [],
            "styles": [],
            "templateUrl": [
                "./labs.component.html"
            ],
            "viewProviders": [],
            "hostDirectives": [],
            "inputsClass": [],
            "outputsClass": [],
            "propertiesClass": [
                {
                    "name": "age",
                    "defaultValue": "29",
                    "deprecated": false,
                    "deprecationMessage": "",
                    "type": "number",
                    "optional": false,
                    "description": "",
                    "line": 21
                },
                {
                    "name": "colorCtrl",
                    "defaultValue": "new FormControl()",
                    "deprecated": false,
                    "deprecationMessage": "",
                    "type": "",
                    "optional": false,
                    "description": "",
                    "line": 30
                },
                {
                    "name": "disabled",
                    "defaultValue": "true",
                    "deprecated": false,
                    "deprecationMessage": "",
                    "type": "",
                    "optional": false,
                    "description": "",
                    "line": 22
                },
                {
                    "name": "img",
                    "defaultValue": "'https://w3schools.com/howto/img_avatar.png'",
                    "deprecated": false,
                    "deprecationMessage": "",
                    "type": "string",
                    "optional": false,
                    "description": "",
                    "line": 23
                },
                {
                    "name": "name",
                    "defaultValue": "signal('Leonardo')",
                    "deprecated": false,
                    "deprecationMessage": "",
                    "type": "",
                    "optional": false,
                    "description": "",
                    "line": 20
                },
                {
                    "name": "nameCtrl",
                    "defaultValue": "new FormControl('leonado', {\n    nonNullable: true,\n    validators: [\n      Validators.required,\n      Validators.minLength(3)\n    ]\n  })",
                    "deprecated": false,
                    "deprecationMessage": "",
                    "type": "",
                    "optional": false,
                    "description": "",
                    "line": 34
                },
                {
                    "name": "person",
                    "defaultValue": "signal({\n    name: 'Leonardo',\n    age: 29,\n    avatar: 'https://w3schools.com/howto/img_avatar.png'\n  })",
                    "deprecated": false,
                    "deprecationMessage": "",
                    "type": "",
                    "optional": false,
                    "description": "",
                    "line": 25
                },
                {
                    "name": "tasks",
                    "defaultValue": "signal([\n    'Instalar Angular CLI',\n    'Crear proyecto',\n    'Crear componente',\n    'Crear servicio',\n  ])",
                    "deprecated": false,
                    "deprecationMessage": "",
                    "type": "",
                    "optional": false,
                    "description": "",
                    "line": 14
                },
                {
                    "name": "welcome",
                    "defaultValue": "'Bienvenido a mi primera aplicación con Angular'",
                    "deprecated": false,
                    "deprecationMessage": "",
                    "type": "string",
                    "optional": false,
                    "description": "",
                    "line": 13
                },
                {
                    "name": "widthCtrl",
                    "defaultValue": "new FormControl(50, {\n    nonNullable: true,\n  })",
                    "deprecated": false,
                    "deprecationMessage": "",
                    "type": "",
                    "optional": false,
                    "description": "",
                    "line": 31
                }
            ],
            "methodsClass": [
                {
                    "name": "changeAge",
                    "args": [
                        {
                            "name": "event",
                            "type": "Event",
                            "deprecated": false,
                            "deprecationMessage": ""
                        }
                    ],
                    "optional": false,
                    "returnType": "void",
                    "typeParameters": [],
                    "line": 63,
                    "deprecated": false,
                    "deprecationMessage": "",
                    "jsdoctags": [
                        {
                            "name": "event",
                            "type": "Event",
                            "deprecated": false,
                            "deprecationMessage": "",
                            "tagName": {
                                "text": "param"
                            }
                        }
                    ]
                },
                {
                    "name": "changeHandler",
                    "args": [
                        {
                            "name": "event",
                            "type": "Event",
                            "deprecated": false,
                            "deprecationMessage": ""
                        }
                    ],
                    "optional": false,
                    "returnType": "void",
                    "typeParameters": [],
                    "line": 53,
                    "deprecated": false,
                    "deprecationMessage": "",
                    "jsdoctags": [
                        {
                            "name": "event",
                            "type": "Event",
                            "deprecated": false,
                            "deprecationMessage": "",
                            "tagName": {
                                "text": "param"
                            }
                        }
                    ]
                },
                {
                    "name": "changeName",
                    "args": [
                        {
                            "name": "event",
                            "type": "Event",
                            "deprecated": false,
                            "deprecationMessage": ""
                        }
                    ],
                    "optional": false,
                    "returnType": "void",
                    "typeParameters": [],
                    "line": 73,
                    "deprecated": false,
                    "deprecationMessage": "",
                    "jsdoctags": [
                        {
                            "name": "event",
                            "type": "Event",
                            "deprecated": false,
                            "deprecationMessage": "",
                            "tagName": {
                                "text": "param"
                            }
                        }
                    ]
                },
                {
                    "name": "clickHandler",
                    "args": [],
                    "optional": false,
                    "returnType": "void",
                    "typeParameters": [],
                    "line": 49,
                    "deprecated": false,
                    "deprecationMessage": ""
                },
                {
                    "name": "keydownHandler",
                    "args": [
                        {
                            "name": "event",
                            "type": "KeyboardEvent",
                            "deprecated": false,
                            "deprecationMessage": ""
                        }
                    ],
                    "optional": false,
                    "returnType": "void",
                    "typeParameters": [],
                    "line": 58,
                    "deprecated": false,
                    "deprecationMessage": "",
                    "jsdoctags": [
                        {
                            "name": "event",
                            "type": "KeyboardEvent",
                            "deprecated": false,
                            "deprecationMessage": "",
                            "tagName": {
                                "text": "param"
                            }
                        }
                    ]
                }
            ],
            "deprecated": false,
            "deprecationMessage": "",
            "hostBindings": [],
            "hostListeners": [],
            "standalone": true,
            "imports": [
                {
                    "name": "CommonModule",
                    "type": "module"
                },
                {
                    "name": "ReactiveFormsModule",
                    "type": "module"
                }
            ],
            "description": "",
            "rawdescription": "\n",
            "type": "component",
            "sourceCode": "import { Component, signal } from '@angular/core';\nimport { CommonModule } from '@angular/common';\nimport { FormControl, ReactiveFormsModule, Validators } from '@angular/forms';\n\n@Component({\n  selector: 'app-labs',\n  standalone: true,\n  imports: [CommonModule, ReactiveFormsModule],\n  templateUrl: './labs.component.html',\n  styleUrl: './labs.component.scss'\n})\nexport class LabsComponent {\n  welcome = 'Bienvenido a mi primera aplicación con Angular';\n  tasks = signal([\n    'Instalar Angular CLI',\n    'Crear proyecto',\n    'Crear componente',\n    'Crear servicio',\n  ]);\n  name = signal('Leonardo');\n  age = 29;\n  disabled = true;\n  img = 'https://w3schools.com/howto/img_avatar.png';\n\n  person = signal({\n    name: 'Leonardo',\n    age: 29,\n    avatar: 'https://w3schools.com/howto/img_avatar.png'\n  });\n  colorCtrl = new FormControl();\n  widthCtrl = new FormControl(50, {\n    nonNullable: true,\n  });\n  nameCtrl = new FormControl('leonado', {\n    nonNullable: true,\n    validators: [\n      Validators.required,\n      Validators.minLength(3)\n    ]\n  });\n\n  constructor() {\n    this.colorCtrl.valueChanges.subscribe(value => {\n      console.log(value);\n    })\n  }\n\n\n  clickHandler() {\n    alert('Hooollla');\n  }\n\n  changeHandler(event: Event) {\n    const input = event.target as HTMLInputElement;\n    const newValue = input.value;\n    this.name.set(newValue);\n  }\n  keydownHandler(event: KeyboardEvent) {\n    const input = event.target as HTMLInputElement;\n    console.log(input.value);\n  }\n\n  changeAge(event: Event) {\n    const input = event.target as HTMLInputElement;\n    const newValue = input.value;\n    this.person.update( prevState => {\n      return {\n        ...prevState, age: parseInt(newValue, 10)\n      }\n    });\n  }\n\n  changeName(event: Event) {\n    const input = event.target as HTMLInputElement;\n    const newValue = input.value;\n    this.person.update( prevState => {\n      return {\n        ...prevState, name: newValue\n      }\n    });\n  }\n}\n",
            "styleUrl": "./labs.component.scss",
            "assetsDirs": [],
            "styleUrlsData": "",
            "stylesData": "",
            "constructorObj": {
                "name": "constructor",
                "description": "",
                "deprecated": false,
                "deprecationMessage": "",
                "args": [],
                "line": 40
            },
            "extends": [],
            "templateData": "<div class=\"container\">\n  <h1>Hola mi primer proyecto</h1>\n  <h2>{{ welcome }}</h2>\n  <ul>\n    @for (task of tasks(); track task) {\n    <li>\n      {{ task }}\n    </li>\n    }\n  </ul>\n  <hr />\n  <h2>{{ 'Hola'.repeat(4) }}</h2>\n  <p> la suma es 3 + 3 es {{ 3 + 3 }}</p>\n  <p>Hola soy {{ name() }} y mi edad es {{ age }}</p>\n  <hr />\n  <img [src]=\"person().avatar\" alt=\"\">\n  <input type=\"number\" [value]=\"person().age\">\n  <button [disabled]=\"disabled\">Click me</button>\n  <p>person: {{ person().name }}</p>\n  <hr />\n  <button (click)=\"clickHandler()\">click me</button>\n  <button (dblclick)=\"clickHandler()\">double me</button>\n  <p>(change)</p>\n  <input type=\"number\" [value]=\"person().age\" (change)=\"changeHandler($event)\">\n  <p>(change)</p>\n  <input type=\"text\" [value]=\"person().name\" (change)=\"changeHandler($event)\">\n  <p>(keydown)</p>\n  <input type=\"text\" [value]=\"person().name\" (keydown)=\"keydownHandler($event)\">\n  <p>(keydown shift )</p>\n  <input type=\"text\" [value]=\"person().name\" (keydown.shift.t)=\"clickHandler()\">\n  <hr />\n  <h1>Signals</h1>\n  <input type=\"text\" [value]=\"name()\" (change)=\"changeHandler($event)\">\n  <p>name: {{ name() }}</p>\n  <p>name: {{ name() }}</p>\n  <hr />\n  <ul>\n    <p>total: {{ tasks().length }}</p>\n    @for (task of tasks(); track task; let i = $index) {\n    <li>\n      {{ i }} {{ task }}\n    </li>\n    }\n  </ul>\n  <hr />\n  @if (1 !== 1) {\n  <div>\n    My contend\n  </div>\n  }\n  @if (name() === 'leonardo') {\n  <div>\n    Soy leonardo\n  </div>\n  }\n  @if (name() === 'Leonardo') {\n  <div>Soy Leonardo</div>\n  }\n  <input type=\"number\" [value]=\"person().age\" (change)=\"changeAge($event)\">\n  @if (person().name === 'leonardo' && person().age > 18) {\n  <div>\n    Soy leonardo y soy mayor de 18\n  </div>\n  } @else {\n\n  Soy leonardo y soy menor de 18\n\n  }\n  <h2>If else new</h2>\n  @if (person().name === 'leonardo' && person().age > 18) {\n  <strong> Soy leonardo y soy mayor de 18</strong>\n  } @else {\n  <i>Soy leonardo y soy menor de 18</i>\n  }\n  <hr />\n  <input type=\"text\" [value]=\"person().name\" (change)=\"changeName($event)\">\n  <div>\n    @switch (person().name) {\n    @case ('leonardo') {\n    <p>yo soy leonardo</p>\n    }\n    @case ('julian') {\n    <p>yo soy julian</p>\n    }\n    @case ('ana') {\n    <p>yo soy ana</p>\n    }\n    @case ('valentina') {\n    <p>yo soy valentina</p>\n    }\n    @default {\n    <p>yo no soy nadie</p>\n    }\n    }\n  </div>\n  <hr />\n  <input type=\"color\" [formControl]=\"colorCtrl\">\n  <p>color: {{ colorCtrl.value }}</p>\n  <svg>\n    <g>\n      <rect x=\"0\" y=\"0\" height=\"100\" width=\"100\" [attr.fill]=\"colorCtrl.value\" />\n    </g>\n  </svg>\n  <hr />\n  <input type=\"number\" [formControl]=\"widthCtrl\">\n  <span class=\"box\" [style.width.px]=\"widthCtrl.value\"></span>\n  <hr />\n  <p>\n    <input type=\"text\" [formControl]=\"nameCtrl\"> <br />\n    <span class=\"message-error\" [class.show]=\"nameCtrl.invalid && nameCtrl.touched\">Nombre invalido</span>\n  </p>\n  <p>\n    <input type=\"text\">\n  </p>\n  <hr />\n  <h2>New for</h2>\n  <ul>\n    <p>total: {{ tasks().length }}</p>\n    @for (task of tasks(); track task; let i = $index) {\n    <li>\n      {{ i }} {{ task }}\n    </li>\n    }\n  </ul>\n  <ul>\n    @for(task of tasks(); track task; let i = $index) {\n    <li>{{ i }} {{ task }}</li>\n    } @empty {\n    <li><strong>la lista esta en vacio</strong></li>\n    }\n  </ul>\n  <hr />\n  <h2>New Switch</h2>\n  <div>\n    @switch (person().name) {\n    @case ('Leonardo') {\n    <p>yo soy leonardo</p>\n    }\n    @case ('julian') {\n    <p>yo soy julian</p>\n    }\n    @case ('ana') {\n    <p>yo soy ana</p>\n    }\n    @case ('valentina') {\n    <p>yo soy valentina</p>\n    }\n    @default {\n    <p>yo no soy nadie</p>\n    }\n    }\n  </div>\n  <div>\n    @switch(person().name) {\n      @case('Leonardo') {\n      <p>yo soy leonardo</p>\n      }\n      @case('julian') {\n      <p>yo soy julian</p>\n      }\n      @case('ana') {\n      <p>yo soy ana</p>\n      }\n      @default {\n      <p>yo no soy nadie</p>\n      }\n    }\n  </div>\n\n</div>"
        },
        {
            "name": "PageComponent",
            "id": "component-PageComponent-d32b0f19628254ea3fc5526c4d4564ada1cc83cf936759006d90a46f5874b02a3359e331bddda20b22e74a616a6443c660602ba74dd38ebe1160759e0de6f7ba",
            "file": "src/stories/page.component.ts",
            "encapsulation": [],
            "entryComponents": [],
            "inputs": [],
            "outputs": [],
            "providers": [],
            "selector": "storybook-page",
            "styleUrls": [
                "./page.css"
            ],
            "styles": [],
            "template": "<article>    <storybook-header\n      [user]=\"user\"\n      (onLogout)=\"doLogout()\"\n      (onLogin)=\"doLogin()\"\n      (onCreateAccount)=\"doCreateAccount()\"\n    ></storybook-header>\n    <section class=\"storybook-page\">\n      <h2>Pages in Storybook</h2>\n      <p>\n        We recommend building UIs with a\n        <a href=\"https://componentdriven.org\" target=\"_blank\" rel=\"noopener noreferrer\">\n          <strong>component-driven</strong>\n        </a>\n        process starting with atomic components and ending with pages.\n      </p>\n      <p>\n        Render pages with mock data. This makes it easy to build and review page states without\n        needing to navigate to them in your app. Here are some handy patterns for managing page data\n        in Storybook:\n      </p>\n      <ul>\n        <li>\n          Use a higher-level connected component. Storybook helps you compose such data from the\n          \"args\" of child component stories\n        </li>\n        <li>\n          Assemble data in the page component from your services. You can mock these services out\n          using Storybook.\n        </li>\n      </ul>\n      <p>\n        Get a guided tutorial on component-driven development at\n        <a href=\"https://storybook.js.org/tutorials/\" target=\"_blank\" rel=\"noopener noreferrer\">\n          Storybook tutorials\n        </a>\n        . Read more in the\n        <a href=\"https://storybook.js.org/docs\" target=\"_blank\" rel=\"noopener noreferrer\"> docs </a>\n        .\n      </p>\n      <div class=\"tip-wrapper\">\n        <span class=\"tip\">Tip</span> Adjust the width of the canvas with the\n        <svg width=\"10\" height=\"10\" viewBox=\"0 0 12 12\" xmlns=\"http://www.w3.org/2000/svg\">\n          <g fill=\"none\" fillRule=\"evenodd\">\n            <path\n              d=\"M1.5 5.2h4.8c.3 0 .5.2.5.4v5.1c-.1.2-.3.3-.4.3H1.4a.5.5 0 01-.5-.4V5.7c0-.3.2-.5.5-.5zm0-2.1h6.9c.3 0 .5.2.5.4v7a.5.5 0 01-1 0V4H1.5a.5.5 0 010-1zm0-2.1h9c.3 0 .5.2.5.4v9.1a.5.5 0 01-1 0V2H1.5a.5.5 0 010-1zm4.3 5.2H2V10h3.8V6.2z\"\n              id=\"a\"\n              fill=\"#999\"\n            />\n          </g>\n        </svg>\n        Viewports addon in the toolbar\n      </div>\n    </section>\n  </article>",
            "templateUrl": [],
            "viewProviders": [],
            "hostDirectives": [],
            "inputsClass": [],
            "outputsClass": [],
            "propertiesClass": [
                {
                    "name": "user",
                    "defaultValue": "null",
                    "deprecated": false,
                    "deprecationMessage": "",
                    "type": "User | null",
                    "optional": false,
                    "description": "",
                    "line": 69
                }
            ],
            "methodsClass": [
                {
                    "name": "doCreateAccount",
                    "args": [],
                    "optional": false,
                    "returnType": "void",
                    "typeParameters": [],
                    "line": 79,
                    "deprecated": false,
                    "deprecationMessage": ""
                },
                {
                    "name": "doLogin",
                    "args": [],
                    "optional": false,
                    "returnType": "void",
                    "typeParameters": [],
                    "line": 75,
                    "deprecated": false,
                    "deprecationMessage": ""
                },
                {
                    "name": "doLogout",
                    "args": [],
                    "optional": false,
                    "returnType": "void",
                    "typeParameters": [],
                    "line": 71,
                    "deprecated": false,
                    "deprecationMessage": ""
                }
            ],
            "deprecated": false,
            "deprecationMessage": "",
            "hostBindings": [],
            "hostListeners": [],
            "standalone": true,
            "imports": [
                {
                    "name": "CommonModule",
                    "type": "module"
                },
                {
                    "name": "HeaderComponent",
                    "type": "component"
                }
            ],
            "description": "",
            "rawdescription": "\n",
            "type": "component",
            "sourceCode": "import { Component } from '@angular/core';\nimport { CommonModule } from '@angular/common';\n\nimport { HeaderComponent } from './header.component';\nimport type { User } from './user';\n\n@Component({\n  selector: 'storybook-page',\n  standalone: true,\n  imports: [CommonModule, HeaderComponent],\n  template: `<article>\n    <storybook-header\n      [user]=\"user\"\n      (onLogout)=\"doLogout()\"\n      (onLogin)=\"doLogin()\"\n      (onCreateAccount)=\"doCreateAccount()\"\n    ></storybook-header>\n    <section class=\"storybook-page\">\n      <h2>Pages in Storybook</h2>\n      <p>\n        We recommend building UIs with a\n        <a href=\"https://componentdriven.org\" target=\"_blank\" rel=\"noopener noreferrer\">\n          <strong>component-driven</strong>\n        </a>\n        process starting with atomic components and ending with pages.\n      </p>\n      <p>\n        Render pages with mock data. This makes it easy to build and review page states without\n        needing to navigate to them in your app. Here are some handy patterns for managing page data\n        in Storybook:\n      </p>\n      <ul>\n        <li>\n          Use a higher-level connected component. Storybook helps you compose such data from the\n          \"args\" of child component stories\n        </li>\n        <li>\n          Assemble data in the page component from your services. You can mock these services out\n          using Storybook.\n        </li>\n      </ul>\n      <p>\n        Get a guided tutorial on component-driven development at\n        <a href=\"https://storybook.js.org/tutorials/\" target=\"_blank\" rel=\"noopener noreferrer\">\n          Storybook tutorials\n        </a>\n        . Read more in the\n        <a href=\"https://storybook.js.org/docs\" target=\"_blank\" rel=\"noopener noreferrer\"> docs </a>\n        .\n      </p>\n      <div class=\"tip-wrapper\">\n        <span class=\"tip\">Tip</span> Adjust the width of the canvas with the\n        <svg width=\"10\" height=\"10\" viewBox=\"0 0 12 12\" xmlns=\"http://www.w3.org/2000/svg\">\n          <g fill=\"none\" fillRule=\"evenodd\">\n            <path\n              d=\"M1.5 5.2h4.8c.3 0 .5.2.5.4v5.1c-.1.2-.3.3-.4.3H1.4a.5.5 0 01-.5-.4V5.7c0-.3.2-.5.5-.5zm0-2.1h6.9c.3 0 .5.2.5.4v7a.5.5 0 01-1 0V4H1.5a.5.5 0 010-1zm0-2.1h9c.3 0 .5.2.5.4v9.1a.5.5 0 01-1 0V2H1.5a.5.5 0 010-1zm4.3 5.2H2V10h3.8V6.2z\"\n              id=\"a\"\n              fill=\"#999\"\n            />\n          </g>\n        </svg>\n        Viewports addon in the toolbar\n      </div>\n    </section>\n  </article>`,\n  styleUrls: ['./page.css'],\n})\nexport class PageComponent {\n  user: User | null = null;\n\n  doLogout() {\n    this.user = null;\n  }\n\n  doLogin() {\n    this.user = { name: 'Jane Doe' };\n  }\n\n  doCreateAccount() {\n    this.user = { name: 'Jane Doe' };\n  }\n}\n",
            "assetsDirs": [],
            "styleUrlsData": [
                {
                    "data": ".storybook-page {\n  font-family: 'Nunito Sans', 'Helvetica Neue', Helvetica, Arial, sans-serif;\n  font-size: 14px;\n  line-height: 24px;\n  padding: 48px 20px;\n  margin: 0 auto;\n  max-width: 600px;\n  color: #333;\n}\n\n.storybook-page h2 {\n  font-weight: 700;\n  font-size: 32px;\n  line-height: 1;\n  margin: 0 0 4px;\n  display: inline-block;\n  vertical-align: top;\n}\n\n.storybook-page p {\n  margin: 1em 0;\n}\n\n.storybook-page a {\n  text-decoration: none;\n  color: #1ea7fd;\n}\n\n.storybook-page ul {\n  padding-left: 30px;\n  margin: 1em 0;\n}\n\n.storybook-page li {\n  margin-bottom: 8px;\n}\n\n.storybook-page .tip {\n  display: inline-block;\n  border-radius: 1em;\n  font-size: 11px;\n  line-height: 12px;\n  font-weight: 700;\n  background: #e7fdd8;\n  color: #66bf3c;\n  padding: 4px 12px;\n  margin-right: 10px;\n  vertical-align: top;\n}\n\n.storybook-page .tip-wrapper {\n  font-size: 13px;\n  line-height: 20px;\n  margin-top: 40px;\n  margin-bottom: 40px;\n}\n\n.storybook-page .tip-wrapper svg {\n  display: inline-block;\n  height: 12px;\n  width: 12px;\n  margin-right: 4px;\n  vertical-align: top;\n  margin-top: 3px;\n}\n\n.storybook-page .tip-wrapper svg path {\n  fill: #1ea7fd;\n}\n",
                    "styleUrl": "./page.css"
                }
            ],
            "stylesData": "",
            "extends": []
        }
    ],
    "modules": [],
    "miscellaneous": {
        "variables": [
            {
                "name": "appConfig",
                "ctype": "miscellaneous",
                "subtype": "variable",
                "file": "src/app/app.config.ts",
                "deprecated": false,
                "deprecationMessage": "",
                "type": "ApplicationConfig",
                "defaultValue": "{\n  providers: [provideRouter(routes)]\n}"
            },
            {
                "name": "Large",
                "ctype": "miscellaneous",
                "subtype": "variable",
                "file": "src/stories/button.stories.ts",
                "deprecated": false,
                "deprecationMessage": "",
                "type": "Story",
                "defaultValue": "{\n  args: {\n    size: 'large',\n    label: 'Button',\n  },\n}"
            },
            {
                "name": "LoggedIn",
                "ctype": "miscellaneous",
                "subtype": "variable",
                "file": "src/stories/header.stories.ts",
                "deprecated": false,
                "deprecationMessage": "",
                "type": "Story",
                "defaultValue": "{\n  args: {\n    user: {\n      name: 'Jane Doe',\n    },\n  },\n}"
            },
            {
                "name": "LoggedIn",
                "ctype": "miscellaneous",
                "subtype": "variable",
                "file": "src/stories/page.stories.ts",
                "deprecated": false,
                "deprecationMessage": "",
                "type": "Story",
                "defaultValue": "{\n  play: async ({ canvasElement }) => {\n    const canvas = within(canvasElement);\n    const loginButton = canvas.getByRole('button', { name: /Log in/i });\n    await expect(loginButton).toBeInTheDocument();\n    await userEvent.click(loginButton);\n    await expect(loginButton).not.toBeInTheDocument();\n\n    const logoutButton = canvas.getByRole('button', { name: /Log out/i });\n    await expect(logoutButton).toBeInTheDocument();\n  },\n}"
            },
            {
                "name": "LoggedOut",
                "ctype": "miscellaneous",
                "subtype": "variable",
                "file": "src/stories/header.stories.ts",
                "deprecated": false,
                "deprecationMessage": "",
                "type": "Story",
                "defaultValue": "{}"
            },
            {
                "name": "LoggedOut",
                "ctype": "miscellaneous",
                "subtype": "variable",
                "file": "src/stories/page.stories.ts",
                "deprecated": false,
                "deprecationMessage": "",
                "type": "Story",
                "defaultValue": "{}"
            },
            {
                "name": "meta",
                "ctype": "miscellaneous",
                "subtype": "variable",
                "file": "src/stories/button.stories.ts",
                "deprecated": false,
                "deprecationMessage": "",
                "type": "Meta<ButtonComponent>",
                "defaultValue": "{\n  title: 'Example/Button',\n  component: ButtonComponent,\n  tags: ['autodocs'],\n  render: (args: ButtonComponent) => ({\n    props: {\n      backgroundColor: null,\n      ...args,\n    },\n  }),\n  argTypes: {\n    backgroundColor: {\n      control: 'color',\n    },\n  },\n}"
            },
            {
                "name": "meta",
                "ctype": "miscellaneous",
                "subtype": "variable",
                "file": "src/stories/header.stories.ts",
                "deprecated": false,
                "deprecationMessage": "",
                "type": "Meta<HeaderComponent>",
                "defaultValue": "{\n  title: 'Example/Header',\n  component: HeaderComponent,\n  // This component will have an automatically generated Autodocs entry: https://storybook.js.org/docs/writing-docs/autodocs\n  tags: ['autodocs'],\n  parameters: {\n    // More on how to position stories at: https://storybook.js.org/docs/configure/story-layout\n    layout: 'fullscreen',\n  },\n}"
            },
            {
                "name": "meta",
                "ctype": "miscellaneous",
                "subtype": "variable",
                "file": "src/stories/page.stories.ts",
                "deprecated": false,
                "deprecationMessage": "",
                "type": "Meta<PageComponent>",
                "defaultValue": "{\n  title: 'Example/Page',\n  component: PageComponent,\n  parameters: {\n    // More on how to position stories at: https://storybook.js.org/docs/configure/story-layout\n    layout: 'fullscreen',\n  },\n}"
            },
            {
                "name": "preview",
                "ctype": "miscellaneous",
                "subtype": "variable",
                "file": ".storybook/preview.ts",
                "deprecated": false,
                "deprecationMessage": "",
                "type": "Preview",
                "defaultValue": "{\n  parameters: {\n    actions: { argTypesRegex: \"^on[A-Z].*\" },\n    controls: {\n      matchers: {\n        color: /(background|color)$/i,\n        date: /Date$/i,\n      },\n    },\n  },\n}"
            },
            {
                "name": "Primary",
                "ctype": "miscellaneous",
                "subtype": "variable",
                "file": "src/stories/button.stories.ts",
                "deprecated": false,
                "deprecationMessage": "",
                "type": "Story",
                "defaultValue": "{\n  args: {\n    primary: true,\n    label: 'Button',\n  },\n}"
            },
            {
                "name": "Secondary",
                "ctype": "miscellaneous",
                "subtype": "variable",
                "file": "src/stories/button.stories.ts",
                "deprecated": false,
                "deprecationMessage": "",
                "type": "Story",
                "defaultValue": "{\n  args: {\n    label: 'Button',\n  },\n}"
            },
            {
                "name": "Small",
                "ctype": "miscellaneous",
                "subtype": "variable",
                "file": "src/stories/button.stories.ts",
                "deprecated": false,
                "deprecationMessage": "",
                "type": "Story",
                "defaultValue": "{\n  args: {\n    size: 'small',\n    label: 'Button',\n  },\n}"
            }
        ],
        "functions": [],
        "typealiases": [
            {
                "name": "Story",
                "ctype": "miscellaneous",
                "subtype": "typealias",
                "rawtype": "StoryObj<ButtonComponent>",
                "file": "src/stories/button.stories.ts",
                "deprecated": false,
                "deprecationMessage": "",
                "description": "",
                "kind": 183
            },
            {
                "name": "Story",
                "ctype": "miscellaneous",
                "subtype": "typealias",
                "rawtype": "StoryObj<HeaderComponent>",
                "file": "src/stories/header.stories.ts",
                "deprecated": false,
                "deprecationMessage": "",
                "description": "",
                "kind": 183
            },
            {
                "name": "Story",
                "ctype": "miscellaneous",
                "subtype": "typealias",
                "rawtype": "StoryObj<PageComponent>",
                "file": "src/stories/page.stories.ts",
                "deprecated": false,
                "deprecationMessage": "",
                "description": "",
                "kind": 183
            }
        ],
        "enumerations": [
            {
                "name": "FilterEnum",
                "childs": [
                    {
                        "name": "ALL",
                        "deprecated": false,
                        "deprecationMessage": "",
                        "value": "ALL"
                    },
                    {
                        "name": "PENDING",
                        "deprecated": false,
                        "deprecationMessage": "",
                        "value": "PENDING"
                    },
                    {
                        "name": "COMPLETED",
                        "deprecated": false,
                        "deprecationMessage": "",
                        "value": "COMPLETED"
                    }
                ],
                "ctype": "miscellaneous",
                "subtype": "enum",
                "deprecated": false,
                "deprecationMessage": "",
                "description": "",
                "file": "src/app/enums/filtes.enum.ts"
            }
        ],
        "groupedVariables": {
            "src/app/app.config.ts": [
                {
                    "name": "appConfig",
                    "ctype": "miscellaneous",
                    "subtype": "variable",
                    "file": "src/app/app.config.ts",
                    "deprecated": false,
                    "deprecationMessage": "",
                    "type": "ApplicationConfig",
                    "defaultValue": "{\n  providers: [provideRouter(routes)]\n}"
                }
            ],
            "src/stories/button.stories.ts": [
                {
                    "name": "Large",
                    "ctype": "miscellaneous",
                    "subtype": "variable",
                    "file": "src/stories/button.stories.ts",
                    "deprecated": false,
                    "deprecationMessage": "",
                    "type": "Story",
                    "defaultValue": "{\n  args: {\n    size: 'large',\n    label: 'Button',\n  },\n}"
                },
                {
                    "name": "meta",
                    "ctype": "miscellaneous",
                    "subtype": "variable",
                    "file": "src/stories/button.stories.ts",
                    "deprecated": false,
                    "deprecationMessage": "",
                    "type": "Meta<ButtonComponent>",
                    "defaultValue": "{\n  title: 'Example/Button',\n  component: ButtonComponent,\n  tags: ['autodocs'],\n  render: (args: ButtonComponent) => ({\n    props: {\n      backgroundColor: null,\n      ...args,\n    },\n  }),\n  argTypes: {\n    backgroundColor: {\n      control: 'color',\n    },\n  },\n}"
                },
                {
                    "name": "Primary",
                    "ctype": "miscellaneous",
                    "subtype": "variable",
                    "file": "src/stories/button.stories.ts",
                    "deprecated": false,
                    "deprecationMessage": "",
                    "type": "Story",
                    "defaultValue": "{\n  args: {\n    primary: true,\n    label: 'Button',\n  },\n}"
                },
                {
                    "name": "Secondary",
                    "ctype": "miscellaneous",
                    "subtype": "variable",
                    "file": "src/stories/button.stories.ts",
                    "deprecated": false,
                    "deprecationMessage": "",
                    "type": "Story",
                    "defaultValue": "{\n  args: {\n    label: 'Button',\n  },\n}"
                },
                {
                    "name": "Small",
                    "ctype": "miscellaneous",
                    "subtype": "variable",
                    "file": "src/stories/button.stories.ts",
                    "deprecated": false,
                    "deprecationMessage": "",
                    "type": "Story",
                    "defaultValue": "{\n  args: {\n    size: 'small',\n    label: 'Button',\n  },\n}"
                }
            ],
            "src/stories/header.stories.ts": [
                {
                    "name": "LoggedIn",
                    "ctype": "miscellaneous",
                    "subtype": "variable",
                    "file": "src/stories/header.stories.ts",
                    "deprecated": false,
                    "deprecationMessage": "",
                    "type": "Story",
                    "defaultValue": "{\n  args: {\n    user: {\n      name: 'Jane Doe',\n    },\n  },\n}"
                },
                {
                    "name": "LoggedOut",
                    "ctype": "miscellaneous",
                    "subtype": "variable",
                    "file": "src/stories/header.stories.ts",
                    "deprecated": false,
                    "deprecationMessage": "",
                    "type": "Story",
                    "defaultValue": "{}"
                },
                {
                    "name": "meta",
                    "ctype": "miscellaneous",
                    "subtype": "variable",
                    "file": "src/stories/header.stories.ts",
                    "deprecated": false,
                    "deprecationMessage": "",
                    "type": "Meta<HeaderComponent>",
                    "defaultValue": "{\n  title: 'Example/Header',\n  component: HeaderComponent,\n  // This component will have an automatically generated Autodocs entry: https://storybook.js.org/docs/writing-docs/autodocs\n  tags: ['autodocs'],\n  parameters: {\n    // More on how to position stories at: https://storybook.js.org/docs/configure/story-layout\n    layout: 'fullscreen',\n  },\n}"
                }
            ],
            "src/stories/page.stories.ts": [
                {
                    "name": "LoggedIn",
                    "ctype": "miscellaneous",
                    "subtype": "variable",
                    "file": "src/stories/page.stories.ts",
                    "deprecated": false,
                    "deprecationMessage": "",
                    "type": "Story",
                    "defaultValue": "{\n  play: async ({ canvasElement }) => {\n    const canvas = within(canvasElement);\n    const loginButton = canvas.getByRole('button', { name: /Log in/i });\n    await expect(loginButton).toBeInTheDocument();\n    await userEvent.click(loginButton);\n    await expect(loginButton).not.toBeInTheDocument();\n\n    const logoutButton = canvas.getByRole('button', { name: /Log out/i });\n    await expect(logoutButton).toBeInTheDocument();\n  },\n}"
                },
                {
                    "name": "LoggedOut",
                    "ctype": "miscellaneous",
                    "subtype": "variable",
                    "file": "src/stories/page.stories.ts",
                    "deprecated": false,
                    "deprecationMessage": "",
                    "type": "Story",
                    "defaultValue": "{}"
                },
                {
                    "name": "meta",
                    "ctype": "miscellaneous",
                    "subtype": "variable",
                    "file": "src/stories/page.stories.ts",
                    "deprecated": false,
                    "deprecationMessage": "",
                    "type": "Meta<PageComponent>",
                    "defaultValue": "{\n  title: 'Example/Page',\n  component: PageComponent,\n  parameters: {\n    // More on how to position stories at: https://storybook.js.org/docs/configure/story-layout\n    layout: 'fullscreen',\n  },\n}"
                }
            ],
            ".storybook/preview.ts": [
                {
                    "name": "preview",
                    "ctype": "miscellaneous",
                    "subtype": "variable",
                    "file": ".storybook/preview.ts",
                    "deprecated": false,
                    "deprecationMessage": "",
                    "type": "Preview",
                    "defaultValue": "{\n  parameters: {\n    actions: { argTypesRegex: \"^on[A-Z].*\" },\n    controls: {\n      matchers: {\n        color: /(background|color)$/i,\n        date: /Date$/i,\n      },\n    },\n  },\n}"
                }
            ]
        },
        "groupedFunctions": {},
        "groupedEnumerations": {
            "src/app/enums/filtes.enum.ts": [
                {
                    "name": "FilterEnum",
                    "childs": [
                        {
                            "name": "ALL",
                            "deprecated": false,
                            "deprecationMessage": "",
                            "value": "ALL"
                        },
                        {
                            "name": "PENDING",
                            "deprecated": false,
                            "deprecationMessage": "",
                            "value": "PENDING"
                        },
                        {
                            "name": "COMPLETED",
                            "deprecated": false,
                            "deprecationMessage": "",
                            "value": "COMPLETED"
                        }
                    ],
                    "ctype": "miscellaneous",
                    "subtype": "enum",
                    "deprecated": false,
                    "deprecationMessage": "",
                    "description": "",
                    "file": "src/app/enums/filtes.enum.ts"
                }
            ]
        },
        "groupedTypeAliases": {
            "src/stories/button.stories.ts": [
                {
                    "name": "Story",
                    "ctype": "miscellaneous",
                    "subtype": "typealias",
                    "rawtype": "StoryObj<ButtonComponent>",
                    "file": "src/stories/button.stories.ts",
                    "deprecated": false,
                    "deprecationMessage": "",
                    "description": "",
                    "kind": 183
                }
            ],
            "src/stories/header.stories.ts": [
                {
                    "name": "Story",
                    "ctype": "miscellaneous",
                    "subtype": "typealias",
                    "rawtype": "StoryObj<HeaderComponent>",
                    "file": "src/stories/header.stories.ts",
                    "deprecated": false,
                    "deprecationMessage": "",
                    "description": "",
                    "kind": 183
                }
            ],
            "src/stories/page.stories.ts": [
                {
                    "name": "Story",
                    "ctype": "miscellaneous",
                    "subtype": "typealias",
                    "rawtype": "StoryObj<PageComponent>",
                    "file": "src/stories/page.stories.ts",
                    "deprecated": false,
                    "deprecationMessage": "",
                    "description": "",
                    "kind": 183
                }
            ]
        }
    },
    "routes": [],
    "coverage": {
        "count": 3,
        "status": "low",
        "files": [
            {
                "filePath": ".storybook/preview.ts",
                "type": "variable",
                "linktype": "miscellaneous",
                "linksubtype": "variable",
                "name": "preview",
                "coveragePercent": 0,
                "coverageCount": "0/1",
                "status": "low"
            },
            {
                "filePath": "src/app/app.component.ts",
                "type": "component",
                "linktype": "component",
                "name": "AppComponent",
                "coveragePercent": 0,
                "coverageCount": "0/1",
                "status": "low"
            },
            {
                "filePath": "src/app/app.config.ts",
                "type": "variable",
                "linktype": "miscellaneous",
                "linksubtype": "variable",
                "name": "appConfig",
                "coveragePercent": 0,
                "coverageCount": "0/1",
                "status": "low"
            },
            {
                "filePath": "src/app/models/task.model.ts",
                "type": "interface",
                "linktype": "interface",
                "name": "Task",
                "coveragePercent": 0,
                "coverageCount": "0/5",
                "status": "low"
            },
            {
                "filePath": "src/app/pages/home/home.component.ts",
                "type": "component",
                "linktype": "component",
                "name": "HomeComponent",
                "coveragePercent": 0,
                "coverageCount": "0/18",
                "status": "low"
            },
            {
                "filePath": "src/app/pages/labs/labs.component.ts",
                "type": "component",
                "linktype": "component",
                "name": "LabsComponent",
                "coveragePercent": 0,
                "coverageCount": "0/17",
                "status": "low"
            },
            {
                "filePath": "src/stories/button.component.ts",
                "type": "component",
                "linktype": "component",
                "name": "ButtonComponent",
                "coveragePercent": 83,
                "coverageCount": "5/6",
                "status": "very-good"
            },
            {
                "filePath": "src/stories/button.stories.ts",
                "type": "variable",
                "linktype": "miscellaneous",
                "linksubtype": "variable",
                "name": "Large",
                "coveragePercent": 0,
                "coverageCount": "0/1",
                "status": "low"
            },
            {
                "filePath": "src/stories/button.stories.ts",
                "type": "variable",
                "linktype": "miscellaneous",
                "linksubtype": "variable",
                "name": "meta",
                "coveragePercent": 0,
                "coverageCount": "0/1",
                "status": "low"
            },
            {
                "filePath": "src/stories/button.stories.ts",
                "type": "variable",
                "linktype": "miscellaneous",
                "linksubtype": "variable",
                "name": "Primary",
                "coveragePercent": 0,
                "coverageCount": "0/1",
                "status": "low"
            },
            {
                "filePath": "src/stories/button.stories.ts",
                "type": "variable",
                "linktype": "miscellaneous",
                "linksubtype": "variable",
                "name": "Secondary",
                "coveragePercent": 0,
                "coverageCount": "0/1",
                "status": "low"
            },
            {
                "filePath": "src/stories/button.stories.ts",
                "type": "variable",
                "linktype": "miscellaneous",
                "linksubtype": "variable",
                "name": "Small",
                "coveragePercent": 0,
                "coverageCount": "0/1",
                "status": "low"
            },
            {
                "filePath": "src/stories/header.component.ts",
                "type": "component",
                "linktype": "component",
                "name": "HeaderComponent",
                "coveragePercent": 0,
                "coverageCount": "0/5",
                "status": "low"
            },
            {
                "filePath": "src/stories/header.stories.ts",
                "type": "variable",
                "linktype": "miscellaneous",
                "linksubtype": "variable",
                "name": "LoggedIn",
                "coveragePercent": 0,
                "coverageCount": "0/1",
                "status": "low"
            },
            {
                "filePath": "src/stories/header.stories.ts",
                "type": "variable",
                "linktype": "miscellaneous",
                "linksubtype": "variable",
                "name": "LoggedOut",
                "coveragePercent": 0,
                "coverageCount": "0/1",
                "status": "low"
            },
            {
                "filePath": "src/stories/header.stories.ts",
                "type": "variable",
                "linktype": "miscellaneous",
                "linksubtype": "variable",
                "name": "meta",
                "coveragePercent": 0,
                "coverageCount": "0/1",
                "status": "low"
            },
            {
                "filePath": "src/stories/page.component.ts",
                "type": "component",
                "linktype": "component",
                "name": "PageComponent",
                "coveragePercent": 0,
                "coverageCount": "0/5",
                "status": "low"
            },
            {
                "filePath": "src/stories/page.stories.ts",
                "type": "variable",
                "linktype": "miscellaneous",
                "linksubtype": "variable",
                "name": "LoggedIn",
                "coveragePercent": 0,
                "coverageCount": "0/1",
                "status": "low"
            },
            {
                "filePath": "src/stories/page.stories.ts",
                "type": "variable",
                "linktype": "miscellaneous",
                "linksubtype": "variable",
                "name": "LoggedOut",
                "coveragePercent": 0,
                "coverageCount": "0/1",
                "status": "low"
            },
            {
                "filePath": "src/stories/page.stories.ts",
                "type": "variable",
                "linktype": "miscellaneous",
                "linksubtype": "variable",
                "name": "meta",
                "coveragePercent": 0,
                "coverageCount": "0/1",
                "status": "low"
            },
            {
                "filePath": "src/stories/user.ts",
                "type": "interface",
                "linktype": "interface",
                "name": "User",
                "coveragePercent": 0,
                "coverageCount": "0/2",
                "status": "low"
            }
        ]
    }
}